setup.py
ctec_thrift_client/__init__.py
ctec_thrift_client/client_pool.py
ctec_thrift_client/error.py
ctec_thrift_client.egg-info/PKG-INFO
ctec_thrift_client.egg-info/SOURCES.txt
ctec_thrift_client.egg-info/dependency_links.txt
ctec_thrift_client.egg-info/requires.txt
ctec_thrift_client.egg-info/top_level.txt