Metadata-Version: 1.0
Name: ctec-thrift-client
Version: 1.0.5
Summary: 189 thrift rpc client
Home-page: http://www.189.cn
Author: ZhangZhaoyuan
Author-email: zhangzhy@chinatelecom.cn
License: UNKNOWN
Platform: UNKNOWN
